parqser/__init__.py
parqser/simple_example.py
parqser/page/__init__.py
parqser/page/base_page.py
parqser/page/download_state.py
parqser/page/loaded_page.py
parqser/parser/__init__.py
parqser/parser/base_parser.py
parqser/parser/html_parser.py
parqser/saver/__init__.py
parqser/saver/base_saver.py
parqser/saver/csv_saver.py
parqser/scrapper/__init__.py
parqser/scrapper/base_scrapper.py
parqser/scrapper/batch_parallel_scrapper.py
parqser/session/__init__.py
parqser/session/base_session.py
parqser/session/empty_session.py
parqser/web_component/__init__.py
parqser/web_component/base_component.py
parqser-1.0.15.dist-info/LICENSE
parqser-1.0.15.dist-info/METADATA
parqser-1.0.15.dist-info/WHEEL
parqser-1.0.15.dist-info/top_level.txt
parqser-1.0.15.dist-info/RECORD
