Metadata-Version: 2.1
Name: parqser
Version: 1.0.15
Summary: Finally, a good parser
Home-page: https://github.com/ARQtty/parqser
Author: Ilya Shamov
Author-email: ShamovIA@yandex.ru
License: MIT
Platform: UNKNOWN
License-File: LICENSE
Requires-Dist: requests
Requires-Dist: lxml
Requires-Dist: loguru
